sopel_boorus/__init__.py
sopel_boorus/errors.py
sopel_boorus/types.py
sopel_boorus/util.py
sopel_boorus/danbooru/__init__.py
sopel_boorus/danbooru/plugin.py
sopel_boorus/danbooru/types.py
sopel_boorus/gelbooru/__init__.py
sopel_boorus/gelbooru/plugin.py
sopel_boorus/gelbooru/types.py
sopel_boorus-0.1.5.dist-info/licenses/COPYING
sopel_boorus-0.1.5.dist-info/METADATA
sopel_boorus-0.1.5.dist-info/WHEEL
sopel_boorus-0.1.5.dist-info/entry_points.txt
sopel_boorus-0.1.5.dist-info/top_level.txt
sopel_boorus-0.1.5.dist-info/RECORD
