Metadata-Version: 2.4
Name: sopel-boorus
Version: 0.1.5
Summary: Image board (booru) plugins for Sopel IRC bots.
Author-email: dgw <dgw@technobabbl.es>
License: EFL-2.0
Project-URL: Homepage, https://github.com/dgw/sopel-boorus
Project-URL: Bug Tracker, https://github.com/dgw/sopel-boorus/issues
Keywords: sopel,plugin,bot,irc
Platform: Linux x86, x86-64
Classifier: Intended Audience :: Developers
Classifier: Intended Audience :: System Administrators
Classifier: License :: Eiffel Forum License (EFL)
Classifier: License :: OSI Approved :: Eiffel Forum License
Classifier: Programming Language :: Python :: 3 :: Only
Classifier: Topic :: Communications :: Chat :: Internet Relay Chat
Requires-Python: <4,>=3.8
License-File: COPYING
Requires-Dist: sopel>=8.0
Requires-Dist: pylru~=1.2.0
Requires-Dist: requests
Dynamic: license-file
